cjm_fasthtml_daisyui/__init__.py
cjm_fasthtml_daisyui/_modidx.py
cjm_fasthtml_daisyui/builders/__init__.py
cjm_fasthtml_daisyui/builders/colors.py
cjm_fasthtml_daisyui/builders/sizes.py
cjm_fasthtml_daisyui/builders/styles.py
cjm_fasthtml_daisyui/cli/__init__.py
cjm_fasthtml_daisyui/cli/cli_config.py
cjm_fasthtml_daisyui/cli/explorer.py
cjm_fasthtml_daisyui/components/__init__.py
cjm_fasthtml_daisyui/components/actions/__init__.py
cjm_fasthtml_daisyui/components/actions/button.py
cjm_fasthtml_daisyui/components/actions/dropdown.py
cjm_fasthtml_daisyui/components/actions/fab.py
cjm_fasthtml_daisyui/components/actions/modal.py
cjm_fasthtml_daisyui/components/actions/swap.py
cjm_fasthtml_daisyui/components/actions/theme_controller.py
cjm_fasthtml_daisyui/components/data_display/__init__.py
cjm_fasthtml_daisyui/components/data_display/accordion.py
cjm_fasthtml_daisyui/components/data_display/avatar.py
cjm_fasthtml_daisyui/components/data_display/badge.py
cjm_fasthtml_daisyui/components/data_display/card.py
cjm_fasthtml_daisyui/components/data_display/carousel.py
cjm_fasthtml_daisyui/components/data_display/chat_bubble.py
cjm_fasthtml_daisyui/components/data_display/collapse.py
cjm_fasthtml_daisyui/components/data_display/countdown.py
cjm_fasthtml_daisyui/components/data_display/diff.py
cjm_fasthtml_daisyui/components/data_display/hover_gallery.py
cjm_fasthtml_daisyui/components/data_display/kbd.py
cjm_fasthtml_daisyui/components/data_display/list.py
cjm_fasthtml_daisyui/components/data_display/stat.py
cjm_fasthtml_daisyui/components/data_display/status.py
cjm_fasthtml_daisyui/components/data_display/table.py
cjm_fasthtml_daisyui/components/data_display/timeline.py
cjm_fasthtml_daisyui/components/data_input/__init__.py
cjm_fasthtml_daisyui/components/data_input/calendar.py
cjm_fasthtml_daisyui/components/data_input/checkbox.py
cjm_fasthtml_daisyui/components/data_input/fieldset.py
cjm_fasthtml_daisyui/components/data_input/file_input.py
cjm_fasthtml_daisyui-0.0.13.dist-info/licenses/LICENSE
cjm_fasthtml_daisyui-0.0.13.dist-info/METADATA
cjm_fasthtml_daisyui-0.0.13.dist-info/WHEEL
cjm_fasthtml_daisyui-0.0.13.dist-info/entry_points.txt
cjm_fasthtml_daisyui-0.0.13.dist-info/top_level.txt
cjm_fasthtml_daisyui-0.0.13.dist-info/RECORD
