Metadata-Version: 2.4
Name: cjm-fasthtml-daisyui
Version: 0.0.13
Summary: Python-native daisyUI v5 component and utility class builder providing dynamic class generation with full abstraction for FastHTML projects.
Home-page: https://github.com/cj-mills/cjm-fasthtml-daisyui
Author: Christian J. Mills
Author-email: 9126128+cj-mills@users.noreply.github.com
License: Apache Software License 2.0
Keywords: nbdev jupyter notebook python
Classifier: Development Status :: 4 - Beta
Classifier: Intended Audience :: Developers
Classifier: Natural Language :: English
Classifier: Programming Language :: Python :: 3.11
Classifier: Programming Language :: Python :: 3.12
Classifier: License :: OSI Approved :: Apache Software License
Requires-Python: >=3.11
License-File: LICENSE
Requires-Dist: python-fasthtml
Requires-Dist: nbformat
Requires-Dist: cjm_fasthtml_tailwind
Provides-Extra: dev
Dynamic: author
Dynamic: author-email
Dynamic: classifier
Dynamic: description
Dynamic: description-content-type
Dynamic: home-page
Dynamic: keywords
Dynamic: license
Dynamic: license-file
Dynamic: provides-extra
Dynamic: requires-dist
Dynamic: requires-python
Dynamic: summary
